pymyui/__init__.py
pymyui/components/__init__.py
pymyui/components/my_button.py
pymyui/components/my_input.py
pymyui/components/my_label.py
pymyui/components/my_layout.py
pymyui/components/my_notify.py
pymyui/controllers/app.py
pymyui-1.0.1.dist-info/LICENSE
pymyui-1.0.1.dist-info/METADATA
pymyui-1.0.1.dist-info/WHEEL
pymyui-1.0.1.dist-info/RECORD
