Metadata-Version: 2.1
Name: pymyui
Version: 1.0.1
Summary: A simple and intuitive Python framework for creating fast desktop interfaces
Home-page: https://github.com/seu-usuario/myui
License: MIT
Keywords: ui,desktop,gui,framework,pyside6,qt,python
Author: Emerson Silva
Requires-Python: >=3.11,<3.14
Classifier: Development Status :: 5 - Production/Stable
Classifier: Intended Audience :: Developers
Classifier: License :: OSI Approved :: MIT License
Classifier: Operating System :: OS Independent
Classifier: Programming Language :: Python :: 3
Classifier: Programming Language :: Python :: 3.11
Classifier: Programming Language :: Python :: 3.12
Classifier: Programming Language :: Python :: 3.13
Classifier: Topic :: Software Development :: Libraries :: Python Modules
Classifier: Topic :: Software Development :: User Interfaces
Requires-Dist: pyside6 (>=6.9.1,<7.0.0)
Project-URL: Repository, https://github.com/seu-usuario/myui
